computing_lib-0.3.6.dist-info/METADATA
computing_lib-0.3.6.dist-info/WHEEL
computing_lib/__init__.py
computing_lib/computing_lib.cp312-win_amd64.pyd
computing_lib-0.3.6.dist-info/RECORD
